document.write(`<div style="position:relative;width:336px;height:280px;">  
<script async src="https://securepubads.g.doubleclick.net/tag/js/gpt.js"></script>
<div id="gpt-passback1">
  <script>
    window.googletag = window.googletag || {cmd: []};
    googletag.cmd.push(function() {
    googletag.defineSlot('/8068523/oneplaystart.com_display_1', [[336, 280], [300, 250]], 'gpt-passback1').addService(googletag.pubads());
    googletag.enableServices();
    googletag.display('gpt-passback1');
    });
  </script>
</div>
<div style="position:absolute;right:0;top:0;width:26px;padding:3px;background:rgba(255,255,255,.95);z-index:2;"><a href="https://edwardcaruajulca.online/eswhik"><img src="https://cdn-icons-png.flaticon.com/512/5390/5390387.png" style="display:block;width:100% !important;height:auto;" /></a></div>
</div>`)
